video_transcription_server/__init__.py
video_transcription_server/cookies copy.txt
video_transcription_server/cookies.txt
video_transcription_server/server.py
video_transcription_server-0.1.2.dist-info/METADATA
video_transcription_server-0.1.2.dist-info/WHEEL
video_transcription_server-0.1.2.dist-info/entry_points.txt
video_transcription_server-0.1.2.dist-info/licenses/LICENSE
video_transcription_server-0.1.2.dist-info/RECORD
