Metadata-Version: 2.4
Name: video-transcription-server
Version: 0.1.2
Summary: MCP server for video transcription using Whisper
Project-URL: Homepage, https://github.com/jairodrigues/video-transcription-server
Project-URL: Repository, https://github.com/jairodrigues/video-transcription-server
Project-URL: Issues, https://github.com/jairodrigues/video-transcription-server/issues
Author-email: Jairo <jairo.goncalves90@gmail.com>
License-File: LICENSE
Keywords: audio,mcp,transcription,video,whisper
Classifier: Development Status :: 4 - Beta
Classifier: Intended Audience :: Developers
Classifier: License :: OSI Approved :: MIT License
Classifier: Programming Language :: Python :: 3
Classifier: Programming Language :: Python :: 3.10
Classifier: Programming Language :: Python :: 3.11
Classifier: Programming Language :: Python :: 3.12
Requires-Python: >=3.10
Requires-Dist: anyio
Requires-Dist: imageio-ffmpeg
Requires-Dist: mcp>=0.1.0
Requires-Dist: numpy<2.0
Requires-Dist: openai-whisper
Requires-Dist: python-dotenv
Requires-Dist: yt-dlp
